{"cameraMode":{"drawMode":0,"name":"Shaded","section":"Shading Mode"},"sceneLighting":true,"audioPlay":false,"sceneViewState":{"showFog":true,"showMaterialUpdate":false,"showSkybox":true,"showFlares":true,"showImageEffects":true,"showParticleSystems":true},"in2DMode":false,"pivot":{"x":0.022174835205078126,"y":2.9398353099823,"z":-1.432180404663086},"rotation":{"x":-0.03780420497059822,"y":0.9329636693000794,"z":-0.10286212712526322,"w":-0.3428851366043091},"size":13.022601127624512,"orthographic":false}